selfshadingcorrection/__init__.py
selfshadingcorrection/find_b_bw.py
selfshadingcorrection/find_rrs.py
selfshadingcorrection/model_rrs.py
selfshadingcorrection/run.py
selfshadingcorrection/theta_water.py
selfshadingcorrection-1.0.2.dist-info/LICENSE
selfshadingcorrection-1.0.2.dist-info/METADATA
selfshadingcorrection-1.0.2.dist-info/WHEEL
selfshadingcorrection-1.0.2.dist-info/top_level.txt
selfshadingcorrection-1.0.2.dist-info/RECORD
