Metadata-Version: 2.1
Name: selfshadingcorrection
Version: 1.0.2
Summary: Applies self-shading correction to water-leaving reflectance measurements collected through the skylight-blocked approach
Author: Yulun Wu
Author-email: yulunwu8@gmail.com
Classifier: Programming Language :: Python :: 3
Requires-Python: >=3.8
License-File: LICENSE
Requires-Dist: pandas
Requires-Dist: numpy
Requires-Dist: scipy
